[{"Matricula":"2DSVJ02N","CantAsientos":453,"CantBanios":2,"OfreceInternet":true,"OfreceComida":false,"CapacidadBodega":1553,"VueloProgramado":true},{"Matricula":"39V9G1RP","CantAsientos":321,"CantBanios":2,"OfreceInternet":true,"OfreceComida":true,"CapacidadBodega":544,"VueloProgramado":false},{"Matricula":"ON1WA76R","CantAsientos":531,"CantBanios":5,"OfreceInternet":true,"OfreceComida":false,"CapacidadBodega":930,"VueloProgramado":false},{"Matricula":"1VC7C38T","CantAsientos":123,"CantBanios":3,"OfreceInternet":false,"OfreceComida":false,"CapacidadBodega":665,"VueloProgramado":true},{"Matricula":"UGBSGR8B","CantAsientos":441,"CantBanios":3,"OfreceInternet":false,"OfreceComida":true,"CapacidadBodega":521,"VueloProgramado":true}]
